criteo_api_marketingsolutions_v2025_10/__init__.py
criteo_api_marketingsolutions_v2025_10/api_client.py
criteo_api_marketingsolutions_v2025_10/api_client_builder.py
criteo_api_marketingsolutions_v2025_10/configuration.py
criteo_api_marketingsolutions_v2025_10/criteo_api_client.py
criteo_api_marketingsolutions_v2025_10/criteo_auth.py
criteo_api_marketingsolutions_v2025_10/criteo_rest.py
criteo_api_marketingsolutions_v2025_10/exceptions.py
criteo_api_marketingsolutions_v2025_10/flow_constants.py
criteo_api_marketingsolutions_v2025_10/model_utils.py
criteo_api_marketingsolutions_v2025_10/rest.py
criteo_api_marketingsolutions_v2025_10/api/__init__.py
criteo_api_marketingsolutions_v2025_10/api/advertiser_api.py
criteo_api_marketingsolutions_v2025_10/api/analytics_api.py
criteo_api_marketingsolutions_v2025_10/api/audience_api.py
criteo_api_marketingsolutions_v2025_10/api/campaign_api.py
criteo_api_marketingsolutions_v2025_10/api/creative_api.py
criteo_api_marketingsolutions_v2025_10/api/gateway_api.py
criteo_api_marketingsolutions_v2025_10/api/reco_api.py
criteo_api_marketingsolutions_v2025_10/apis/__init__.py
criteo_api_marketingsolutions_v2025_10/model/__init__.py
criteo_api_marketingsolutions_v2025_10/model/ad.py
criteo_api_marketingsolutions_v2025_10/model/ad_set_audience_link_entity_v1.py
criteo_api_marketingsolutions_v2025_10/model/ad_set_audience_link_entity_v1_resource.py
criteo_api_marketingsolutions_v2025_10/model/ad_set_audience_link_entity_v1_response.py
criteo_api_marketingsolutions_v2025_10/model/ad_set_audience_link_input_entity_v1.py
criteo_api_marketingsolutions_v2025_10/model/ad_set_category_bid.py
criteo_api_marketingsolutions_v2025_10/model/ad_set_category_bid_list_response.py
criteo_api_marketingsolutions_v2025_10/model/ad_set_category_bid_resource.py
criteo_api_marketingsolutions_v2025_10/model/ad_set_delivery_limitations_v24_q3.py
criteo_api_marketingsolutions_v2025_10/model/ad_set_delivery_status.py
criteo_api_marketingsolutions_sdk-2025.10.0.251229.dist-info/METADATA
criteo_api_marketingsolutions_sdk-2025.10.0.251229.dist-info/WHEEL
criteo_api_marketingsolutions_sdk-2025.10.0.251229.dist-info/top_level.txt
criteo_api_marketingsolutions_sdk-2025.10.0.251229.dist-info/RECORD
